netconf_client/__init__.py
netconf_client/connect.py
netconf_client/constants.py
netconf_client/error.py
netconf_client/log.py
netconf_client/ncclient.py
netconf_client/parser.py
netconf_client/rpc.py
netconf_client/session.py
netconf_client-3.5.0.dist-info/COPYING
netconf_client-3.5.0.dist-info/METADATA
netconf_client-3.5.0.dist-info/WHEEL
netconf_client-3.5.0.dist-info/RECORD
