Metadata-Version: 2.1
Name: netconf-client
Version: 3.5.0
Summary: A Python NETCONF client
Home-page: https://github.com/ADTRAN/netconf_client
License: Apache-2.0
Keywords: netconf
Author: ADTRAN, Inc.
Requires-Python: >=3.8,<4.0
Classifier: Development Status :: 5 - Production/Stable
Classifier: Intended Audience :: Telecommunications Industry
Classifier: License :: OSI Approved :: Apache Software License
Classifier: Operating System :: OS Independent
Classifier: Programming Language :: Python :: 3
Classifier: Programming Language :: Python :: 3.8
Classifier: Programming Language :: Python :: 3.9
Classifier: Programming Language :: Python :: 3.10
Classifier: Programming Language :: Python :: 3.11
Requires-Dist: lxml (>=4.6.3,<7)
Requires-Dist: paramiko (>=2.7.2,<5)
Project-URL: Documentation, https://adtran.github.io/netconf_client/
Project-URL: Repository, https://github.com/ADTRAN/netconf_client
